discrete_model/__init__.py
discrete_model/discrete_model.py
discrete_model/influence_graph.py
discrete_model/parser.py
discrete_model-0.1.2.dist-info/METADATA
discrete_model-0.1.2.dist-info/RECORD
discrete_model-0.1.2.dist-info/WHEEL
discrete_model-0.1.2.dist-info/top_level.txt
